{"matchID": "EUW1_7537557044", "timestamp": 1758662196829, "achiev": {"firstTowerAssist": true, "firstTowerKill": false, "firstBloodAssist": false, "firstBloodKill": false, "damageSelfMitigated": 16468, "doubleKills": 0, "highDamagePerDeath": false, "highkda": false, "lane": "BOTTOM", "earlyStats": ["earlyLaningPhaseGoldExpAdvantage", "takedownsFirstXMinutes", "turretPlatesTaken", "kTurretsDestroyedBeforePlatesFall", "landSkillShotsEarlyGame"], "dodgeSkillShotsSmallWindow": 0, "acesBefore15Minutes": 0, "quickCleanse": 0, "quickFirstTurret": 0, "quickSoloKills": 0, "skillshotsDodged": 18, "skillshotsHit": 6, "fullTeamTakedown": 0, "killingSprees": 0, "riftHeraldTakedowns": 0, "killParticipation": 0.7, "multiKillOneSpell": 0, "deathsByEnemyChamps": 6, "maxCsAdvantageOnLaneOpponent": 2, "maxLevelLeadLaneOpponent": 1, "teamDamagePercentage": 0.08367262201539832, "soloKills": 0}, "power": {"fistBumpParticipation": 0, "pings": {}, "goldEarnedperMin": 302.95601173020526, "goldSpentperMin": 276.24633431085044, "magicDamageDealt": 18710, "magicDamageDealtToChampions": 5245, "magicDamageTaken": 5513, "physicalDamageDealt": 5034, "physicalDamageDealtToChampions": 1044, "physicalDamageTaken": 15395}, "hed": {"takedownsInEnemyFountain": 0, "alliedJungleMonsterKills": 0, "twentyMinionsIn3SecondsCount": 0, "blastConeOppositeOpponentCount": 0}, "stim": {"deaths": 6, "damageSelfMitigated": 16468, "bountyGold": 201.04269409179688, "buffsStolen": 0, "elderDragonKillsWithOpposingSoul": 0, "junglerTakedownsNearDamagedEpicMonster": 0, "epicMonsterKillsNearEnemyJungler": 0, "epicMonsterSteals": 0, "killsNearEnemyTurret": 2, "survivedSingleDigitHpCount": 0, "survivedThreeImmobilizesInFight": 2}, "selfD": {"goldEarnedperMin": 302.95601173020526, "goldSpentperMin": 276.24633431085044, "championName": "Karma", "championId": 43, "killAfterHiddenWithAlly": 1, "knockEnemyIntoTeamAndKill": 0, "killsWithHelpFromEpicMonster": 0, "legendaryItemUsed": [3870, 3107, 2065], "multiTurretRiftHeraldCount": 0, "takedownsAfterGainingLevelAdvantage": 0, "takedownsInAlcove": 0, "soloKills": 0, "unseenRecalls": 0}, "bene": {}, "trad": {"csPerMin": 0.8797653958944281, "csPerMinPre10": 1.1}, "univ": {"lane": "BOTTOM", "championId": 43}, "secs": {"deaths": 6, "damageSelfMitigated": 16468, "longestTimeSpentLiving": 724, "consumablesPurchased": 8, "deathsByEnemyChamps": 6, "hadOpenNexus": 0, "lostAnInhibitor": 0, "killsUnderOwnTurret": 0, "scuttleCrabKills": 0, "visionScoreAdvantageLaneOpponent": 0.10123968124389648, "visionScorePerMinute": 2.184068716196953, "wardTakedowns": 3, "wardsGuarded": 0}}