{"matchID": "EUW1_7458490991", "timestamp": 1752260874307, "achiev": {"firstTowerAssist": true, "firstTowerKill": false, "firstBloodAssist": false, "firstBloodKill": false, "damageSelfMitigated": 2900, "doubleKills": 0, "highDamagePerDeath": true, "highkda": false, "lane": "BOTTOM", "earlyStats": ["earlyLaningPhaseGoldExpAdvantage", "takedownsFirstXMinutes", "turretPlatesTaken", "kTurretsDestroyedBeforePlatesFall", "landSkillShotsEarlyGame"], "dodgeSkillShotsSmallWindow": 0, "acesBefore15Minutes": 0, "quickCleanse": 0, "quickFirstTurret": 0, "quickSoloKills": 0, "skillshotsDodged": 11, "skillshotsHit": 0, "fullTeamTakedown": 0, "killingSprees": 0, "riftHeraldTakedowns": 0, "killParticipation": 0.5, "multiKillOneSpell": 0, "deathsByEnemyChamps": 2, "maxCsAdvantageOnLaneOpponent": 12, "maxLevelLeadLaneOpponent": 2, "teamDamagePercentage": 0.21501143031795206, "soloKills": 0}, "power": {"fistBumpParticipation": 0, "pings": {}, "goldEarnedperMin": 299.9511400651466, "goldSpentperMin": 283.38762214983717, "magicDamageDealt": 12828, "magicDamageDealtToChampions": 9809, "magicDamageTaken": 2677, "physicalDamageDealt": 3599, "physicalDamageDealtToChampions": 959, "physicalDamageTaken": 5686}, "hed": {"takedownsInEnemyFountain": 0, "alliedJungleMonsterKills": 0, "twentyMinionsIn3SecondsCount": 0, "blastConeOppositeOpponentCount": 0}, "stim": {"deaths": 2, "damageSelfMitigated": 2900, "bountyGold": 0, "buffsStolen": 0, "elderDragonKillsWithOpposingSoul": 0, "junglerTakedownsNearDamagedEpicMonster": 0, "epicMonsterKillsNearEnemyJungler": 0, "epicMonsterSteals": 0, "killsNearEnemyTurret": 1, "survivedSingleDigitHpCount": 0, "survivedThreeImmobilizesInFight": 0}, "selfD": {"goldEarnedperMin": 299.9511400651466, "goldSpentperMin": 283.38762214983717, "championName": "Teemo", "championId": 17, "killAfterHiddenWithAlly": 0, "knockEnemyIntoTeamAndKill": 0, "killsWithHelpFromEpicMonster": 0, "legendaryItemUsed": [3871, 6653], "multiTurretRiftHeraldCount": 0, "takedownsAfterGainingLevelAdvantage": 0, "takedownsInAlcove": 0, "soloKills": 0, "unseenRecalls": 0}, "bene": {}, "trad": {"csPerMin": 1.465798045602606, "csPerMinPre10": 1.8}, "univ": {"lane": "BOTTOM", "championId": 17}, "secs": {"deaths": 2, "damageSelfMitigated": 2900, "longestTimeSpentLiving": 514, "consumablesPurchased": 8, "deathsByEnemyChamps": 2, "hadOpenNexus": 0, "lostAnInhibitor": 0, "killsUnderOwnTurret": 0, "scuttleCrabKills": 0, "visionScoreAdvantageLaneOpponent": 0.3161717653274536, "visionScorePerMinute": 2.4020149866321385, "wardTakedowns": 7, "wardsGuarded": 0}}