{"matchID": "EUW1_7466669267", "timestamp": 1752955651473, "achiev": {"firstTowerAssist": false, "firstTowerKill": false, "firstBloodAssist": true, "firstBloodKill": false, "damageSelfMitigated": 49031, "doubleKills": 0, "highDamagePerDeath": false, "highkda": false, "lane": "BOTTOM", "earlyStats": ["earlyLaningPhaseGoldExpAdvantage", "takedownsFirstXMinutes", "turretPlatesTaken", "kTurretsDestroyedBeforePlatesFall", "landSkillShotsEarlyGame"], "dodgeSkillShotsSmallWindow": 8, "acesBefore15Minutes": 0, "quickCleanse": 0, "quickFirstTurret": 0, "quickSoloKills": 0, "skillshotsDodged": 126, "skillshotsHit": 24, "fullTeamTakedown": 1, "killingSprees": 0, "riftHeraldTakedowns": 0, "killParticipation": 0.4375, "multiKillOneSpell": 0, "deathsByEnemyChamps": 9, "maxCsAdvantageOnLaneOpponent": 17, "maxLevelLeadLaneOpponent": 1, "teamDamagePercentage": 0.10148323787188634, "soloKills": 0}, "power": {"fistBumpParticipation": 0, "pings": {}, "goldEarnedperMin": 257.89858382823206, "goldSpentperMin": 252.16994061215166, "magicDamageDealt": 24613, "magicDamageDealtToChampions": 8321, "magicDamageTaken": 13861, "physicalDamageDealt": 10703, "physicalDamageDealtToChampions": 3075, "physicalDamageTaken": 17739}, "hed": {"takedownsInEnemyFountain": 0, "alliedJungleMonsterKills": 0, "twentyMinionsIn3SecondsCount": 0, "blastConeOppositeOpponentCount": 0}, "stim": {"deaths": 9, "damageSelfMitigated": 49031, "bountyGold": 0, "buffsStolen": 0, "elderDragonKillsWithOpposingSoul": 0, "junglerTakedownsNearDamagedEpicMonster": 0, "epicMonsterKillsNearEnemyJungler": 0, "epicMonsterSteals": 0, "killsNearEnemyTurret": 0, "survivedSingleDigitHpCount": 0, "survivedThreeImmobilizesInFight": 6}, "selfD": {"goldEarnedperMin": 257.89858382823206, "goldSpentperMin": 252.16994061215166, "championName": "Leona", "championId": 89, "killAfterHiddenWithAlly": 0, "knockEnemyIntoTeamAndKill": 0, "killsWithHelpFromEpicMonster": 0, "legendaryItemUsed": [3190, 3869, 3075, 2504], "multiTurretRiftHeraldCount": 0, "takedownsAfterGainingLevelAdvantage": 0, "takedownsInAlcove": 0, "soloKills": 0, "unseenRecalls": 0}, "bene": {}, "trad": {"csPerMin": 1.3156692553677478, "csPerMinPre10": 1.0}, "univ": {"lane": "BOTTOM", "championId": 89}, "secs": {"deaths": 9, "damageSelfMitigated": 49031, "longestTimeSpentLiving": 330, "consumablesPurchased": 4, "deathsByEnemyChamps": 9, "hadOpenNexus": 0, "lostAnInhibitor": 0, "killsUnderOwnTurret": 0, "scuttleCrabKills": 0, "visionScoreAdvantageLaneOpponent": 0.21681642532348633, "visionScorePerMinute": 2.4918070362932245, "wardTakedowns": 12, "wardsGuarded": 0}}