{"matchID": "EUW1_7534233801", "timestamp": 1758383550880, "achiev": {"firstTowerAssist": false, "firstTowerKill": false, "firstBloodAssist": true, "firstBloodKill": false, "damageSelfMitigated": 8927, "doubleKills": 0, "highDamagePerDeath": false, "highkda": false, "lane": "BOTTOM", "earlyStats": ["earlyLaningPhaseGoldExpAdvantage", "takedownsFirstXMinutes", "turretPlatesTaken", "kTurretsDestroyedBeforePlatesFall", "landSkillShotsEarlyGame"], "dodgeSkillShotsSmallWindow": 0, "acesBefore15Minutes": 0, "quickCleanse": 0, "quickFirstTurret": 0, "quickSoloKills": 0, "skillshotsDodged": 14, "skillshotsHit": 43, "fullTeamTakedown": 0, "killingSprees": 0, "riftHeraldTakedowns": 1, "killParticipation": 0.5, "multiKillOneSpell": 0, "deathsByEnemyChamps": 5, "maxCsAdvantageOnLaneOpponent": 5, "maxLevelLeadLaneOpponent": 1, "teamDamagePercentage": 0.08665319240931699, "soloKills": 0}, "power": {"fistBumpParticipation": 0, "pings": {}, "goldEarnedperMin": 294.18, "goldSpentperMin": 239.99999999999997, "magicDamageDealt": 19502, "magicDamageDealtToChampions": 7392, "magicDamageTaken": 10478, "physicalDamageDealt": 4913, "physicalDamageDealtToChampions": 718, "physicalDamageTaken": 6959}, "hed": {"takedownsInEnemyFountain": 0, "alliedJungleMonsterKills": 0, "twentyMinionsIn3SecondsCount": 0, "blastConeOppositeOpponentCount": 0}, "stim": {"deaths": 5, "damageSelfMitigated": 8927, "bountyGold": 530.2788696289062, "buffsStolen": 0, "elderDragonKillsWithOpposingSoul": 0, "junglerTakedownsNearDamagedEpicMonster": 0, "epicMonsterKillsNearEnemyJungler": 0, "epicMonsterSteals": 0, "killsNearEnemyTurret": 0, "survivedSingleDigitHpCount": 0, "survivedThreeImmobilizesInFight": 0}, "selfD": {"goldEarnedperMin": 294.18, "goldSpentperMin": 239.99999999999997, "championName": "Soraka", "championId": 16, "killAfterHiddenWithAlly": 0, "knockEnemyIntoTeamAndKill": 0, "killsWithHelpFromEpicMonster": 0, "legendaryItemUsed": [3869, 3107, 6621], "multiTurretRiftHeraldCount": 0, "takedownsAfterGainingLevelAdvantage": 0, "takedownsInAlcove": 0, "soloKills": 0, "unseenRecalls": 0}, "bene": {}, "trad": {"csPerMin": 1.17, "csPerMinPre10": 1.6}, "univ": {"lane": "BOTTOM", "championId": 16}, "secs": {"deaths": 5, "damageSelfMitigated": 8927, "longestTimeSpentLiving": 887, "consumablesPurchased": 9, "deathsByEnemyChamps": 5, "hadOpenNexus": 0, "lostAnInhibitor": 0, "killsUnderOwnTurret": 1, "scuttleCrabKills": 1, "visionScoreAdvantageLaneOpponent": 0.26364409923553467, "visionScorePerMinute": 2.9525066789336702, "wardTakedowns": 19, "wardsGuarded": 1}}