{"matchID": "EUW1_7457169436", "timestamp": 1752147989418, "achiev": {"firstTowerAssist": false, "firstTowerKill": false, "firstBloodAssist": false, "firstBloodKill": false, "damageSelfMitigated": 8379, "doubleKills": 0, "highDamagePerDeath": false, "highkda": false, "lane": "BOTTOM", "earlyStats": ["earlyLaningPhaseGoldExpAdvantage", "takedownsFirstXMinutes", "turretPlatesTaken", "kTurretsDestroyedBeforePlatesFall", "landSkillShotsEarlyGame"], "dodgeSkillShotsSmallWindow": 0, "acesBefore15Minutes": 0, "quickCleanse": 0, "quickFirstTurret": 0, "quickSoloKills": 0, "skillshotsDodged": 13, "skillshotsHit": 0, "fullTeamTakedown": 0, "killingSprees": 0, "riftHeraldTakedowns": 0, "killParticipation": 0.5, "multiKillOneSpell": 0, "deathsByEnemyChamps": 11, "maxCsAdvantageOnLaneOpponent": 4, "maxLevelLeadLaneOpponent": 1, "teamDamagePercentage": 0.17303326142229206, "soloKills": 0}, "power": {"fistBumpParticipation": 0, "pings": {}, "goldEarnedperMin": 298.9325153374233, "goldSpentperMin": 280.67484662576686, "magicDamageDealt": 40964, "magicDamageDealtToChampions": 10104, "magicDamageTaken": 8483, "physicalDamageDealt": 5351, "physicalDamageDealtToChampions": 1584, "physicalDamageTaken": 14592}, "hed": {"takedownsInEnemyFountain": 0, "alliedJungleMonsterKills": 0, "twentyMinionsIn3SecondsCount": 0, "blastConeOppositeOpponentCount": 0}, "stim": {"deaths": 11, "damageSelfMitigated": 8379, "bountyGold": 0, "buffsStolen": 0, "elderDragonKillsWithOpposingSoul": 0, "junglerTakedownsNearDamagedEpicMonster": 0, "epicMonsterKillsNearEnemyJungler": 0, "epicMonsterSteals": 0, "killsNearEnemyTurret": 1, "survivedSingleDigitHpCount": 0, "survivedThreeImmobilizesInFight": 0}, "selfD": {"goldEarnedperMin": 298.9325153374233, "goldSpentperMin": 280.67484662576686, "championName": "Teemo", "championId": 17, "killAfterHiddenWithAlly": 1, "knockEnemyIntoTeamAndKill": 0, "killsWithHelpFromEpicMonster": 0, "legendaryItemUsed": [3871, 3118, 3102], "multiTurretRiftHeraldCount": 0, "takedownsAfterGainingLevelAdvantage": 0, "takedownsInAlcove": 0, "soloKills": 0, "unseenRecalls": 0}, "bene": {}, "trad": {"csPerMin": 1.6196319018404908, "csPerMinPre10": 0.7}, "univ": {"lane": "BOTTOM", "championId": 17}, "secs": {"deaths": 11, "damageSelfMitigated": 8379, "longestTimeSpentLiving": 417, "consumablesPurchased": 7, "deathsByEnemyChamps": 11, "hadOpenNexus": 0, "lostAnInhibitor": 0, "killsUnderOwnTurret": 0, "scuttleCrabKills": 0, "visionScoreAdvantageLaneOpponent": -0.3132505416870117, "visionScorePerMinute": 1.2074633363019704, "wardTakedowns": 3, "wardsGuarded": 1}}