{"matchID": "EUW1_7458095121", "timestamp": 1752234183437, "achiev": {"firstTowerAssist": false, "firstTowerKill": false, "firstBloodAssist": false, "firstBloodKill": false, "damageSelfMitigated": 39007, "doubleKills": 0, "highDamagePerDeath": false, "highkda": false, "lane": "BOTTOM", "earlyStats": ["earlyLaningPhaseGoldExpAdvantage", "takedownsFirstXMinutes", "turretPlatesTaken", "kTurretsDestroyedBeforePlatesFall", "landSkillShotsEarlyGame"], "dodgeSkillShotsSmallWindow": 0, "acesBefore15Minutes": 0, "quickCleanse": 0, "quickFirstTurret": 0, "quickSoloKills": 0, "skillshotsDodged": 24, "skillshotsHit": 0, "fullTeamTakedown": 4, "killingSprees": 0, "riftHeraldTakedowns": 0, "killParticipation": 0.6153846153846154, "multiKillOneSpell": 0, "deathsByEnemyChamps": 13, "maxCsAdvantageOnLaneOpponent": 37, "maxLevelLeadLaneOpponent": 1, "teamDamagePercentage": 0.10957780947999171, "soloKills": 1}, "power": {"fistBumpParticipation": 0, "pings": {}, "goldEarnedperMin": 353.27536231884056, "goldSpentperMin": 294.2028985507246, "magicDamageDealt": 4741, "magicDamageDealtToChampions": 1668, "magicDamageTaken": 11858, "physicalDamageDealt": 43225, "physicalDamageDealtToChampions": 13388, "physicalDamageTaken": 31125}, "hed": {"takedownsInEnemyFountain": 0, "alliedJungleMonsterKills": 0, "twentyMinionsIn3SecondsCount": 0, "blastConeOppositeOpponentCount": 0}, "stim": {"deaths": 13, "damageSelfMitigated": 39007, "bountyGold": 718.91748046875, "buffsStolen": 0, "elderDragonKillsWithOpposingSoul": 0, "junglerTakedownsNearDamagedEpicMonster": 0, "epicMonsterKillsNearEnemyJungler": 0, "epicMonsterSteals": 0, "killsNearEnemyTurret": 2, "survivedSingleDigitHpCount": 0, "survivedThreeImmobilizesInFight": 4}, "selfD": {"goldEarnedperMin": 353.27536231884056, "goldSpentperMin": 294.2028985507246, "championName": "JarvanIV", "championId": 59, "killAfterHiddenWithAlly": 3, "knockEnemyIntoTeamAndKill": 0, "killsWithHelpFromEpicMonster": 0, "legendaryItemUsed": [3119, 3877, 3179, 3121, 6609], "multiTurretRiftHeraldCount": 0, "takedownsAfterGainingLevelAdvantage": 0, "takedownsInAlcove": 0, "soloKills": 1, "unseenRecalls": 0}, "bene": {}, "trad": {"csPerMin": 1.7391304347826086, "csPerMinPre10": 1.7}, "univ": {"lane": "BOTTOM", "championId": 59}, "secs": {"deaths": 13, "damageSelfMitigated": 39007, "longestTimeSpentLiving": 237, "consumablesPurchased": 8, "deathsByEnemyChamps": 13, "hadOpenNexus": 0, "lostAnInhibitor": 1, "killsUnderOwnTurret": 0, "scuttleCrabKills": 0, "visionScoreAdvantageLaneOpponent": -0.05261045694351196, "visionScorePerMinute": 2.1743963366994628, "wardTakedowns": 12, "wardsGuarded": 0}}